cloudshell/__init__.py
cloudshell/huawei/__init__.py
cloudshell/huawei/autoload/__init__.py
cloudshell/huawei/autoload/huawei_generic_snmp_autoload.py
cloudshell/huawei/cli/__init__.py
cloudshell/huawei/cli/huawei_cli_handler.py
cloudshell/huawei/cli/huawei_command_modes.py
cloudshell/huawei/command_actions/__init__.py
cloudshell/huawei/command_actions/add_remove_vlan_actions.py
cloudshell/huawei/command_actions/enable_disable_snmp_actions.py
cloudshell/huawei/command_actions/firmware_actions.py
cloudshell/huawei/command_actions/save_restore_actions.py
cloudshell/huawei/command_actions/system_actions.py
cloudshell/huawei/command_templates/__init__.py
cloudshell/huawei/command_templates/add_remove_vlan.py
cloudshell/huawei/command_templates/configuration.py
cloudshell/huawei/command_templates/enable_disable_snmp.py
cloudshell/huawei/command_templates/firmware.py
cloudshell/huawei/command_templates/system.py
cloudshell/huawei/flows/__init__.py
cloudshell/huawei/flows/huawei_autoload_flow.py
cloudshell/huawei/flows/huawei_configuration_flow.py
cloudshell/huawei/flows/huawei_connectivity_flow.py
cloudshell/huawei/flows/huawei_disable_snmp_flow.py
cloudshell/huawei/flows/huawei_enable_snmp_flow.py
cloudshell/huawei/flows/huawei_load_firmware_flow.py
cloudshell/huawei/flows/huawei_run_command_flow.py
cloudshell/huawei/flows/huawei_state_flow.py
cloudshell/huawei/helpers/__init__.py
cloudshell/huawei/helpers/exceptions.py
cloudshell/huawei/mibs/HUAWEI-IMA-MIB.py
cloudshell/huawei/mibs/HUAWEI-MIB.py
cloudshell/huawei/mibs/HUAWEI-PORT-MIB.py
cloudshell/huawei/mibs/HUAWEI-TC-MIB.py
cloudshell/huawei/mibs/P-BRIDGE-MIB.py
cloudshell/huawei/mibs/__init__.py
cloudshell/huawei/snmp/__init__.py
cloudshell/huawei/snmp/huawei_snmp_handler.py
tests/__init__.py
tests/huawei/__init__.py
tests/huawei/flows/__init__.py
tests/huawei/flows/test_huawei_enable_snmp_flow.py
cloudshell_huawei-4.0.1.dist-info/LICENSE.htm
cloudshell_huawei-4.0.1.dist-info/METADATA
cloudshell_huawei-4.0.1.dist-info/WHEEL
cloudshell_huawei-4.0.1.dist-info/top_level.txt
cloudshell_huawei-4.0.1.dist-info/RECORD
